{
    "COVER PAGE": {
        "text": "DCMO SUBJECT : Senior Executive Service ( SES ) , Senior Level ( SL ) and Scientific and Professional ( ST ) Personnel Categories in the Do D Fourth Estate : Executive Resources Management References : See Enclosure 1"
    },
    "1 .PURPOSE": {
        "text": "",
        "a . ": {
            "text": "Instruction .This instruction reissues Do D Directive ( Do DD ) 1402.3 ( Reference ( a ) ) as an instruction in accordance with the authority in Do DI 5105.82 and Deputy Secretary of Defense Memorandum ( References ( b ) and ( c ) ) .It is composed of multiple volumes , each containing its own purpose .The purpose of the overall instruction is to establish policy , assign responsibilities , delegate authorities , and provide Do D Fourth Estate entities with supplemental guidance to the policy , laws , and regulations relevant to the administration of the SES , SL , and ST categories , in accordance with Do DD 1403.1 ( Reference ( d ) ) , and pursuant to Title 5 , United States Code ( U.S.C . ) ( Reference ( e ) ) and Title 5 , Code of Federal Regulations ( Reference ( f ) ) ."
        },
        "b . ": {
            "text": "Volume .This volume :",
            "( 1 )": {
                "text": "Establishes policy , assigns responsibilities , and provides procedures for SES executive resources management ."
            },
            "( 2 )": {
                "text": "Establishes the Do D Fourth Estate Executive Resources Board ( ERB ) pursuant to section 3393 ( b ) of Reference ( e ) and section 317.501 of Reference ( f ) to provide oversight of SES executive resources programs ."
            },
            "( 3 )": {
                "text": "Incorporates and cancels chapter 1 of Do D 1402.3 H ( Reference ( g ) ) and Director of Administration and Management Memorandum ( Reference ( h ) ) ."
            }
        }
    },
    "2 . APPLICABILITY": {
        "text": ".This volume :",
        "a . ": {
            "text": "Applies to OSD , the Office of the Chairman of the Joint Chiefs of Staff and the Joint Staff , the Defense Agencies , the Do D Field Activities , and all other organizational entities in the"
        },
        "b . ": {
            "text": "Does not apply to :",
            "( 1 )": {
                "text": "The Office of the Inspector General of the Department of Defense ."
            },
            "( 2 )": {
                "text": "Those persons in the Defense Intelligence SES and Defense Intelligence Senior Level positions , established under section 1601 of Title 10 , U.S.C . ( Reference ( i ) ) ."
            },
            "( 3 )": {
                "text": "Expert and consultant appointments pursuant to section 3109 of Reference ( e ) or highly qualified expert appointments pursuant to section 9903 of Reference ( e ) ."
            }
        }
    },
    "3 . POLICY": {
        "text": ".It is Do D policy that SES executive resources are managed responsibly through ongoing review and analysis , while ensuring SES allocations are distributed to meet mission priorities and pursuant to Reference ( e ) ."
    },
    "4 . RESPONSIBILITIES": {
        "text": ".See Enclosure 2"
    },
    "5 .PROCEDURES": {
        "text": ".See Enclosure 3"
    },
    "6 .RELEASABILITY": {
        "text": ".Cleared for public release .This volume is available on the Do D Issuances Website at http://www.dtic.mil/whs/directives ."
    },
    "7 . SUMMARY OF CHANGE": {
        "text": "2 .The changes to this volume are administrative and update organizational titles , acronyms , and references for accuracy ."
    },
    "8 . EFFECTIVE DATE": {
        "text": ".This volume : is effective April 30 , 2014 ."
    },
    "4 . ERB G": {
        "text": "lossary. REFERENCES ( a )Do D Directive 1402.3 , “ Administration of the Senior Executive Service Program in the Office of the Secretary of Defense and the Defense Agencies , ” August 16 , 1984 ( cancelled by volume 1 of this instruction ) ( b )Do D Directive 5105.82 , “ Deputy Chief Management Officer ( DCMO ) of the Department of Defense , ” October 17 , 2008",
        "( c )": {
            "text": "Deputy Secretary of Defense Memorandum , “ Reorganization of the Office of the Deputy Chief Management Officer , ” July 11 , 2014",
            "( d )": {
                "text": "Do D Directive 1403.1 , “ The Senior Executive Service and Equivalent Level Positions and Personnel , ” October 18 , 1982",
                "( e )": {
                    "text": "Title 5 , United States Code"
                },
                "( f )": {
                    "text": "Title 5 , Code of Federal Regulations"
                },
                "( g )": {
                    "text": "Chapter 1 of Do D Handbook 1402.3 H , “ Executive Resources Board , ” May 1985 ( hereby cancelled ) ( h )Director of Administration and Management Memorandum , “ SES Resource Allocation Committee , ” November 14 , 2007 ( hereby cancelled ) ( i )Title 10 , United States Code"
                },
                "( j )": {
                    "text": "United States Government Policy and Supporting Positions , 2013 ( Plum Book ) ( k )Do D Directive 1403.03 , “ The Career Lifecycle Management of the Senior Executive Service Leaders Within the Department of Defense , ” October 25 , 2007. RESPONSIBILITIES"
                }
            }
        }
    },
    "1 .DEPUTY CHIEF MANAGEMENT OFFICER OF THE DEPARTMENT OF DEFENSE": {
        "text": ".The Deputy Chief Management Officer , through the Director of Administration , Office of the Deputy Chief Management Officer ( DA ODCMO ) :",
        "a . ": {
            "text": "Serves as the vice chair of the ERB and approves ERB membership ."
        },
        "b . ": {
            "text": "Issues internal written operating procedures for the Do D Fourth Estate implementing the provisions of part 317 , subpart E of Reference ( f ) regarding executive resources management ."
        },
        "c . ": {
            "text": "Approves and reallocates resources and makes tier designations under the authority , direction , and control of the Deputy Secretary of Defense ( Dep Sec Def ) ."
        },
        "d . ": {
            "text": "Delegates the authority bestowed by the Secretary of Defense ( Sec Def ) as deemed appropriate to provide oversight of civilian personnel management within the Fourth Estate , and other assigned activities , to include the management , coordination , appointment , evaluation , and compensation of executive and political personnel in OSD and other assigned Fourth Estate activities ."
        }
    },
    "2 . UNDER SECRETARY OF DEFENSE FOR PERSONNEL AND READINESS ( USD ( P&R ) )": {
        "text": ".The USD ( P&R ) :",
        "a . ": {
            "text": "Possesses full authority for total force management to include all Do D civilian personnel requirements ."
        },
        "b . ": {
            "text": "Exercises overall supervision and policy oversight of human capital .In this capacity , the USD ( P&R ) allocates civilian personnel authorizations to the Do D Components relating to civilian personnel , whether established by law , regulation , or other action .The USD ( P&R ) is the liaison with the U.S . Office of Personnel Management ( OPM ) for SES allocations and policy direction .3 . Do D FOURTH ESTATE COMPONENT HEADS .The Do D Fourth Estate Component heads ensure that nominations for the ERB are provided in accordance with the procedures in this volume and that their organization actively engages in the ERB and associated committees and panels by providing members upon request .. PROCEDURES"
        }
    },
    "1 .EXECUTIVE RESOURCES MANAGEMENT": {
        "text": ".The OPM is responsible for leadership and oversight of the SES and other executive personnel systems government wide , and each federal agency head makes decisions regarding how best to use the executive spaces OPM allocates to the agency .How well each agency manages its executive resources determines its ability to accomplish its mission and to improve government , both through the quality of the executives it attracts and retains and the teamwork that good management creates .Within the Do D Fourth Estate , executive resources are managed primarily through the ERB ."
    },
    "2 . EXECUTIVE RESOURCES PLANNING": {
        "text": ".The executive resources planning process begins with a strategic analysis of current and future executive resource needs , followed by on going evaluations as vacancies become available and mission requirements change .Do D Fourth Estate Component heads will :",
        "a . ": {
            "text": "Identify current and anticipated vacancies of SES , SL , and ST positions ."
        },
        "b . ": {
            "text": "Analyze the organization to eliminate unnecessary management layers ."
        },
        "c . ": {
            "text": "Review each vacant and occupied position in terms of mission , strategic plans and budget projections , and identify positions that will be abolished or restructured to reflect new priorities and goals ."
        },
        "d . ": {
            "text": "Analyze positions to determine if individual positions are classifiable above the GS 15 level and if they will be SES , SL , or ST positions ."
        },
        "e . ": {
            "text": "Prioritize supportable SES , SL , or ST positions ."
        }
    },
    "3 . EXECUTIVE RESOURCES EVALUATION": {
        "text": ".Do D Fourth Estate Component heads will monitor SES resources on a continuous basis to ensure that SES positions are used to respond effectively to changing conditions .It is good management to reassess and reprioritize SES positions in light of the organization ’s current program requirements , either on an ad hoc basis ( as they become vacant ) or as part of a comprehensive review .This identifies any changes in the duties and responsibilities of the positions since they were established or last reviewed .The approach to an SES position review provides a systematic basis to reaffirm or adjust the distribution of SES resources and respond to an organization ’s current requirements .Organizations will monitor SES resource management on a continuous basis to ensure that SES positions are used to respond effectively to changing conditions .Periodic evaluations , especially those in advance of the biennial allocation request to OPM , will take into account :",
        "a . ": {
            "text": "The extent to which the organization has successfully accomplished its mission objectives ; changes in program priorities and emphasis , as reflected in budget or legislative developments ; or the vacancy attrition rate ."
        },
        "b . ": {
            "text": "The number of vacant SES positions , the length of their vacancy , and circumstances surrounding vacancies where the request to recruit has not been initiated within 90 days of the vacancy ."
        },
        "c . ": {
            "text": "Changes in the duties and responsibilities of individual SES positions that could affect the extent to which the positions continue to satisfy SES criteria ."
        }
    },
    "4 . ALLOCATION MANAGEMENT": {
        "text": "",
        "a . ": {
            "text": "OPM allocates spaces to the head of each federal agency on a biennial cycle as specified in law .Flexibility is built into the allocation process to allow for necessary adjustments ; however , the extent of such adjustments is limited .Organizations are expected to manage their executive resource needs within the levels set during the biennial allocation process to include :",
            "( 1 )": {
                "text": "Reprogramming existing resources to meet the agency ’s highest priority requirements ."
            },
            "( 2 )": {
                "text": "Maintaining sufficient flexibility to meet unanticipated needs .When it is not possible to accommodate needs in a timely manner , the Washington Headquarters Services ( WHS ) , Human Resources Directorate ( HRD ) , OSD Senior Executive Management Office ( SEMO ) will work with Do D Fourth Estate entities to identify alternatives to include the possible use of a temporary allocation ."
            }
        },
        "b . ": {
            "text": "The OSD SEMO manages the allocation of SES and equivalent positions under the DA ODCMO ’s purview ."
        },
        "c . ": {
            "text": "Allocations are distributed among OSD Principal Staff Assistants ( PSAs ) by the DA ODCMO based on Do D missions , requirements , and historical composition .If a PSA ’s requirements exceed the established allocations , Do D Fourth Estate entities can request for a Secretary of Defense Reserve Pool ( SDRP ) or lapse rate resource .A justification for the resource along with full recruitment documentation , as established in volume 3 of this instruction , is required .SDRP and lapse rate resources are temporary in nature , not to exceed 2 years in length .Enduring requirements must be submitted as part of the biennial review or outof cycle request process .Additionally , manpower billets must also be obtained for SES allocations in order to establish a position ."
        }
    },
    "5 . BIENNIAL REVIEW": {
        "text": ".Pursuant to section 3133 of Reference ( g ) , during each evennumbered calendar year , the Do D must examine their SES position needs and submit a written request to OPM for a specific number of SES position allocations for the two succeeding fiscal years ( FYs )( e.g . , a request in December 2010 , which is in FY 2011 , would be for the FY",
        "a . ": {
            "text": "Justifications for Requests .Submissions for new allocations under the biennial review must identify the specific positions ( by title and organizational location ) .Justifications must be accompanied with position descriptions and organizational charts .",
            "( 1 )": {
                "text": "Describe the circumstances for the need ( e.g . , legislative mandate or Presidential directive ; new agency mission or expanded agency program ; succession planning requirements or issues raised by the Office of Management and Budget ( OMB ) ; mission requirement ; span of control ; and reporting relationship ) ."
            },
            "( 2 )": {
                "text": "Identify source of funding or other resources to support the new or expanded initiative ( s ) .If resources are reprogrammed within the Do D , identify the functions from which resources are being diverted ."
            },
            "( 3 )": {
                "text": "Specify the results expected from each additional position ( e.g . , improvement in program management or efficiency or meeting administration goals ) ."
            }
        },
        "b . ": {
            "text": "Submission Priorities .Submissions must prioritize all current ( i.e . , established ) and proposed positions , whether vacant or encumbered , in terms of their relative contributions to the agency ’s mission requirements .",
            "( 1 )": {
                "text": "Organizational wide goals and objectives must be identified and prioritized .While an executive may believe a particular position ( e.g . , a deputy or assistant ) is critical to his or her specific program area , the position may not rank as high in relation to the organization ’s mission ."
            },
            "( 2 )": {
                "text": "Positions in the lowest priority category are those that present opportunities for reprogramming of executive resources , ( i.e . , positions that may be filled at a lower level or abolished ) , as turnover occurs , or positions from which the current incumbent may be reassigned if an appropriate opportunity is identified .Provide an analysis ( including estimated time frames ) of how the organization can best meet its highest priority needs by redirecting resources from lower priority areas ."
            },
            "( 3 )": {
                "text": "Other considerations may also include changes in functions or programs , overall funding levels , number of vacancies and length of time vacant , and the extent positions do not appear to meet SES criteria ."
            }
        }
    },
    "6 . OUT OF CYCLE REQUESTS": {
        "text": ".OPM gives Do D the opportunity to submit out of cycle requests in the event new , high priority requirements emerge between biennial reviews and existing resources are exhausted .When the USD ( P&R ) issues a call for requests for additional resources , the OSD SEMO will forward that request to the Fourth Estate entities and require the information outlined in section 5 of this enclosure be provided .. Change 2 , 04/20/2017 11 ENCLOSURE 3"
    },
    "7 .NON SES ALLOCATIONS": {
        "text": ".The biennial SES allocation cycle is also used to obtain SL and ST allocations as described in section 5 of this enclosure ."
    },
    "8 . TEMPORARY ALLOCATIONS FOR DEVELOPMENTAL PURPOSES": {
        "text": ".OPM may grant a temporary space to support a federal agency sending an executive or senior professional on a short term assignment ( e.g . , an interagency detail ) , during which the individual occupies an agency space even though he or she is not available to work for the agency .The temporary space compensates an agency because the executive continues to fill an agency space while on detail .Examples of short term assignments include certain intra agency details , Intergovernmental Personnel Act ( IPA ) Mobility Program assignments , short term transfers that involve a re employment right ( e.g . , to an international organization ) , and short term reassignments if the position to which the individual would be reassigned cannot be established within the agency ’s current allocation .Requests for a temporary space should be submitted to the OSD SEMO .Information required for a temporary allocation to support continuing development of an SES , SL , or ST employee , includes :",
        "a . ": {
            "text": "The individual 's name , position , organizational component , location , and current appointment type ."
        },
        "b . ": {
            "text": "Description of the developmental assignment .Identify the position to which the individual will be assigned ; the type of assignment , ( e.g . , detail , transfer , reassignment ) , including any applicable statutory or regulatory authority , such as the IPA Mobility Program or details or transfers to international organizations ; the agency , organizational component and location ; and the planned duration of the assignment ."
        },
        "c . ": {
            "text": "Identification of the challenges or development opportunities the assignment will provide that the individual has not had in previous positions ."
        },
        "d . ": {
            "text": "Description of the agency ’s future plans for the individual , presuming the anticipated benefits of the developmental assignments are fully realized , including the position ( s ) that this assignment will prepare the individual to assume ."
        }
    },
    "9 . POSITION DESIGNATIONS": {
        "text": ".SES positions are designated as either general or career reserved .",
        "a . ": {
            "text": "General Positions .General positions may be filled by career , non career , or limited appointees .The same general position may be filled by a career appointee at one time and by a non career or limited appointee at another time .However , a career reserved position must be filled by a career appointee .There are no non career or career positions in the SES , only noncareer or career appointments .General positions are listed in the United States Government Policy and Supporting Positions ( Reference ( j ) ) , published every 4 years after the Presidential election ."
        },
        "b . ": {
            "text": "Career Reserved Positions .A position should be designated career reserved if it must be filled by a career appointee to ensure the impartiality , or the public ’s confidence in the",
            "( 1 )": {
                "text": "These positions involve day to day operations that are not responsible for , or substantially involved in , the determination or public advocacy of major controversial policies of the administration or Do D in these occupational disciplines : adjudication and appeals ; audit and inspection ; civil or criminal law enforcement and compliance ; contract administration and procurement ; grants administration ; investigation and security matters ; or tax liability , including the assessment or collection of taxes and the preparation or review of interpretative opinions ."
            },
            "( 2 )": {
                "text": "Career reserved positions also include :",
                "( a )": {
                    "text": "Scientific or other highly technical or professional positions where duties and responsibilities must be filled by career appointees to ensure impartiality ."
                },
                "( b )": {
                    "text": "Other positions requiring impartiality or the public ’s confidence in impartiality , as determined by the Do D agency in light of its mission ."
                },
                "( c )": {
                    "text": "Positions that are specifically required by law to be career reserved or to be filled by a career appointee ."
                }
            }
        },
        "c . ": {
            "text": "Changing Position Designations .Once a position designation has been made , it may not be changed without written approval from OPM .Requests for designation changes should be sent to WHS , HRD , OSD SEMO .The request should be submitted by the Principal Staff Assistant and describe the circumstances that warrant the change in designation ."
        }
    },
    "10 .APPOINTMENT AUTHORITIES": {
        "text": ".There are four types of SES appointment authorities : career , non career , limited term , and limited emergency ( sections 3132 ( a ) , 3393 , and 3394 of Reference ( e ) and Part 317 , subparts E and F of Reference ( f ) ) .",
        "a . ": {
            "text": "Non Career Appointment Authority .Non career appointment allocations for all Do D Components are made to the Sec Def .Adjustments in the number of SES appointment authorities are limited by law .",
            "( 1 )": {
                "text": "Pursuant to section 3134 of Reference ( e ) , the total number of SES non career appointees in all agencies may not exceed 10 percent of the total number of SES positions in all agencies .Additionally , the total number of SES non career appointees may not at any time exceed the greater of 25 percent of the total number of Do D ’s SES positions ; or the number of positions filled on October 13 , 1978 by non career executive assignments under subpart F of part 305 of Reference ( f ) , as in effect on such date ; or total number of appointments to level IV or V of the Executive Schedule not requiring Senate confirmation , as of that date ."
            },
            "( 2 )": {
                "text": "Each use of a non career appointment authority must be approved individually by OPM , and the authority reverts to OPM upon departure of the incumbent .In this way , OPM continuously resets the number of non career appointment authorities in each agency , ensures the"
            },
            "( 3 )": {
                "text": "The OSD SEMO initiates a request for a non career appointment authority by entering the request into OPM ’s Executive and Schedule C System ( ESCS ) .Each request must be for a named individual to fill a specific SES general position .",
                "( a )": {
                    "text": "ESCS generates an OPM Form 1652 , “ Request for SES Appointment Authority , ” for documentation of approvals .This form , along with a resume or autobiography and a position description , is coordinated with the White House Liaison Office and approved by the DA ODCMO .After completing the OPM Form 1652 , the OSD SEMO forwards it to OPM ."
                },
                "( b )": {
                    "text": "Upon OPM approval , the individual may be appointed to the position upon the previous incumbent ’s departure .There is no provision for overlap or dual incumbency of a position .SES non career appointment authorities are made on a case by case basis and are valid only for the individual and position approved ."
                }
            }
        },
        "b . ": {
            "text": "Limited Appointment Authority .Pursuant to section 3134 ( e ) of Reference ( e ) , the total number of limited term appointees and limited emergency appointees may not exceed 5 percent of the total number of SES positions in all agencies .",
            "( 1 )": {
                "text": "Pursuant to section 317.601 of Reference ( f ) , Do D is provided a pool of limited appointment authorities equal to 3 percent of Do D ’s total SES allocations .These authorities may be used by the Sec Def without prior OPM approval .The appointee must be a career or career type appointee ( or an appointment of equivalent tenure ) in a permanent civil service position outside the SES .The pool authorities may not be used to appoint a retired SES member .Any use of of a limited appointment authority other than as described in this paragraph must be approved individually by OPM , and the authority reverts to OPM upon departure of the incumbent , unless otherwise provided by OPM ."
            },
            "( 2 )": {
                "text": "OPM approval of a limited appointment authority does not imply authorization of an additional SES space allocation .",
                "( a )": {
                    "text": "Limited term and limited emergency appointments count against the Do D ’s SES allocation ."
                },
                "( b )": {
                    "text": "An additional SES allocation must be requested by the OSD SEMO if there is no available allocation to use to appoint an approved limited term or limited emergency appointee ."
                },
                "( c )": {
                    "text": "Requests for limited term and limited emergency appointment authorities are considered on an ad hoc basis upon submission of a written justification that outlines the circumstances warranting use of the authority ."
                },
                "( d )": {
                    "text": "Requests for limited term appointments are also created in ESCS by the OSD SEMO ."
                },
                "( e )": {
                    "text": "OPM must approve each authority outside of the Do D 3 percent pool .Generally , agencies are expected to exhaust their pool authorities before requesting OPM approval of a limited term or limited emergency appointment authority , provided the proposed appointee meets the requirement for holding career or career type appointments outside the SES .. ERB"
                }
            }
        }
    },
    "1 .ERB PURPOSE": {
        "text": ".In accordance with section 317.501 of Reference ( f ) , the Sec Def appoints one or more ERBs to conduct the merit staffing process for career appointments .Additionally , the ERB performs the strategic planning processes as defined in Do DD 1403.03 ( Reference ( k ) ) , with knowledge of SES staffing , tier management , talent and succession management , and executive development functions for the Do D Fourth Estate .Positions classified as “ Defense Intelligence SES ” are excluded in accordance with the provisions of Reference ( k ) ."
    },
    "2 . ERB MEMBERSHIP": {
        "text": ".The Do D Fourth Estate primary ERB comprises permanent members that meet as required to address critical , high level executive issues involving significant departmental impact .A subordinate , working ERB presides over day to day management of executive matters such as facilitation of merit staffing procedures , tier designation determinations , executive development , and talent and succession management .",
        "a . ": {
            "text": "Permanent Membership .The permanent membership of the ERB is designated by position , including the roles of chair , vice chair , and executive secretary .However , if the Sec Def has designated an individual to serve as chair , that individual only serves for a 2 year term .",
            "( 1 )": {
                "text": "ERB Chair .The Sec Def designates the ERB Chair .This position is usually held by the Dep Sec Def , but may be filled from among the Under Secretaries or Assistant Secretaries of Defense , as necessary .The ERB Chair :",
                "( a )": {
                    "text": "Convenes ERB meetings , as required , to provide effective governance over SES lifecycle management ."
                },
                "( b )": {
                    "text": "Presides over the ERB and establishes ERB committees to facilitate the accomplishment of ERB business ."
                }
            },
            "( 2 )": {
                "text": "ERB Vice Chair .The DA ODCMO serves as the ERB Vice Chair .The vice chair works in concert with the chair in managing activities of the ERB and serves with full authority in the chair ’s absence ."
            },
            "( 3 )": {
                "text": "ERB Executive Secretary .The Director , HRD , serves as the ERB Executive Secretary and is a non voting member of the ERB .This designation may be re delegated by the Director , HRD .The Assistant Director ( AD ) , OSD SEMO , serves as the alternate Executive Secretary for the ERB and subsequent panels requiring documentation .The alternate ERB Executive Secretary is a non voting member of the ERB ."
            },
            "( 4 )": {
                "text": "Under Secretary of Defense for Acquisition , Technology , and Logistics"
            },
            "( 5 )": {
                "text": "Under Secretary of Defense for Policy"
            },
            "( 6 )": {
                "text": "Under Secretary of Defense ( Comptroller ) /Chief Financial Officer , Department of Defense"
            },
            "( 7 )": {
                "text": "USD ( P&R )"
            },
            "( 8 )": {
                "text": "Deputy Chief Management Officer"
            },
            "( 9 )": {
                "text": "Do D Chief Information Officer"
            }
        },
        "b . ": {
            "text": "Sub ERB Membership .The primary function of the Sub ERB is to conduct merit staffing functions .The Sub ERB serves as an executive pool used to establish necessary committees and panels requiring executive representation .The AD , OSD SEMO , solicits nominations to maintain Sub ERB membership .All Sub ERB members are submitted for approval by the DA ODCMO on an annual basis or as needed or requested by the AD , OSD SEMO .Sub ERB members are determined based on each PSA ’s and the Joint Chiefs of Staff ’s respective SES allocation and comprises a diverse group of men , women , and functional areas of expertise .",
            "( 1 )": {
                "text": "Nominations for the Sub ERB are solicited annually from the Do D Fourth Estate Component heads .",
                "( a )": {
                    "text": "Members are appointed by the DA ODCMO ."
                },
                "( b )": {
                    "text": "Members must be career or non career SES members , presidential appointees , Defense Intelligence Senior Executives or commissioned officers of the uniformed services serving on active duty at the O 7 level or above , and within the Do D Fourth Estate .However , in order to provide continuity and institutional memory , the majority of membership is career SES members ."
                },
                "( c )": {
                    "text": "Members are designated from among top line management officials with responsibility for a major portion of their organization ’s budget and significant numbers of the organization 's SES positions ."
                },
                "( d )": {
                    "text": "The number of members serving on the ERB is based on the SES population within the Do D Fourth Estate ."
                }
            },
            "( 2 )": {
                "text": "Members are appointed for 2 year terms .For purposes of continuity , replacement members serve new 2 year terms .Existing members continue to serve until new membership and replacement members are approved ."
            }
        },
        "c . ": {
            "text": "Ad Hoc Members .Ad hoc members may be called by the chair or vice chair to provide advice , insight , and assistance as required .. Change 2 , 04/20/2017 17 ENCLOSURE 4"
        }
    },
    "3 .SUB ERB COMMITTEES OR PANELS": {
        "text": ".Committees and panels will be established as needed to support Sub ERB requirements related to SES matters .Some committees designated as standing committees , as those described in this section , must be composed of at least one or more permanent Sub ERB members ( unless otherwise indicated ) and approved by the DA ODCMO .Heads of these committees and panels is based on seniority .",
        "a . ": {
            "text": "Executive Evaluation Panel ( EEP ) .In accordance with section 3393of Reference ( e ) , an ERB is required to review and evaluate all competitive merit staffing functions associated with recruitment for SES vacancies , to include selection , pay setting , and assignments .For the Do D Fourth Estate , EEPs serve as ad hoc panels that perform the competitive merit staffing responsibilities .Operating procedures for the EEP are in volume 3 of this instruction .While the EEP constitutes the Sub ERB ’s largest role , sub ERB membership is also used to provide evaluation and certification of the completion of program requirements for Presidential Management Fellows in accordance with part 362 , subpart D , of Reference ( f ) ."
        },
        "b . ": {
            "text": "EEP Membership .The EEP comprises of at least three SES members , or their military equivalent ( i.e . , 07 level or higher ) , including a chair , a member of the ERB , and a third member from outside the hiring component or supervisory chain .At least one Sub ERB member must be on the EEP and is responsible for the :",
            "( 1 )": {
                "text": "Review of technical and executive qualifications of each candidate for a position to be filled competitively by a career appointee ."
            },
            "( 2 )": {
                "text": "Oversight of the minority and female recruitment outreach efforts of candidates recommended for referral , if desired ."
            },
            "( 3 )": {
                "text": "Validation or modification and approval of referral certificates of best qualified candidates proposed by panel members .Modifications ( e.g . , omission or administrative error ) must be revalidated by the ERB member ."
            },
            "( 4 )": {
                "text": "EEP certifies that merit staffing procedures are conducted in accordance with section 317.501 ( c ) of Reference ( f ) ."
            }
        },
        "c . ": {
            "text": "Tiers .The Do D Fourth Estate uses a three tier structure as a means of ensuring comparability and transparency in executive positions and compensation management across the department .The tier structure is built upon the foundational principle that executive positions vary in terms of impact on mission , level of complexity , span of control , inherent authority , scope and breadth of responsibility , and influence in joint , national security matters .The tier structure is a tool to promote a common understanding of position differences , a common perspective about the relationship of these differences in mission outcomes , and a common language to identify these differences .",
            "( 1 )": {
                "text": "Executive positions are sorted into three tiers based upon the position characteristics described in Tables 1 , 2 , and 3 in the appendix of this enclosure .The hierarchy resembles the general or flag officer ( GO/FO ) hierarchy with tier one positions ( one star equivalent ) generally having less complexity and impact on mission outcomes and tier three positions( three star"
            },
            "( 2 )": {
                "text": "Enterprise positions are generally designated as tier three positions as well as other executive positions meeting the characteristics described in Table 1 of the appendix to this enclosure ."
            }
        },
        "d . ": {
            "text": "Tier Management .This is the process of evaluating SES positions ( career , non career , limited term and limited emergency ) for placement in one of three tiers based upon the position characteristics for each tier .Tier management is performed by the Tier Management Panel ( TMP ) .",
            "( 1 )": {
                "text": "TMP members are assigned certain organizations for review of position tier designations .Positions are reviewed by a pre determined two member team and endorsed by the TMP chair .If there is no consensus , all tier panel members are called to review the position ."
            },
            "( 2 )": {
                "text": "For requests for new SES positions , the TMP chair requests a recommendation from the TMP members who originally reviewed positions in the requesting organization .If the reviewing TMP two member team is in agreement with the PSA ’s or Joint Chiefs of Staff ’s request for placement , the tier panel will agree .If the TMP two member team is not in agreement , the TMP chair discusses with all tier panel members and reaches a consensus .The TMP chair approves all requests for positions at the tier one level that meet the grade level and functional criteria for placement in the SES .There is no requirement for additional review or discussion ."
            },
            "( 3 )": {
                "text": "For changes to existing positions , the TMP chair asks TMP members to review and meet to discuss with all members , whether agreed to by the original two member team or not ."
            },
            "( 4 )": {
                "text": "If the TMP does not agree with a PSA or Joint Chiefs of Staff ’s recommendation , the PSA may present additional , stronger evidence or justification for his or her recommendation .The TMP chair , along with TMP members who reviewed the request , meets with the PSA to try to resolve the issues .If there is no resolution between the TMP and PSA , the position goes forward to the DA ODCMO for decision .Both parties present their rationale to the AD , EPP Division , who prepares the decision package to the DA ODCMO for final resolution ."
            },
            "( 5 )": {
                "text": "Organizations submitting tier requests for new requirements must include :",
                "( a )": {
                    "text": "A justification statement that describes the scope of responsibility for the new requirements , the particular unforeseen mission critical emergency giving rise to the need ( e.g . , legislative mandate , Presidential directive , or Sec Def requirement ) ."
                },
                "( b )": {
                    "text": "The level of responsibility , complexity of portfolio , scope of influence , and impact on mission of the new or revised position ."
                },
                "( c )": {
                    "text": "The number and grades of the personnel the incumbent would supervise ( for supervisory positions ) including the tier level of any subordinate SES position ."
                },
                "( d )": {
                    "text": "The signed OF 8 ( Position Description ) for each proposed new SES ."
                },
                "( e )": {
                    "text": "The organizational charts highlighting where the position resides within the organization and structure under the newly established position .Charts should depict the position ’s peers and subordinates"
                }
            },
            "( 6 )": {
                "text": "The DA ODCMO administers periodic tier reviews of the Do D Fourth Estate to ensure consistency and equity across the Do D Fourth Estate ."
            }
        },
        "e . ": {
            "text": "Executive Development Committee ( EDC ) .The EDC oversees the administration of SES executive development policies , plans , and programs and provides advice and recommendations to the Sec Def regarding long range needs and problems and related procedures or activities .The EDC is responsible for :",
            "( 1 )": {
                "text": "Annual review and revision , as appropriate , of executive development plans ."
            },
            "( 2 )": {
                "text": "Evaluation and certification of the completion of program requirements for each participant in the Presidential Management Fellow and Senior Fellow program , in accordance with part 362 , subpart D , of Reference ( f ) ."
            },
            "( 3 )": {
                "text": "Approval of leave , leave without pay , or career break planning ."
            },
            "( 4 )": {
                "text": "Establishment of parameters for an SES candidate development program ( CDP ) and approval of individual development plans for each participant in the SES CDP in accordance with part 412 , subpart C of Reference ( f ) ."
            }
        },
        "f . ": {
            "text": "Talent and Succession Management Panel .This panel is responsible for :",
            "( 1 )": {
                "text": "Performing a comprehensive strategic planning process to assess organizational and individual SES capabilities to meet mission requirements"
            }
        }
    }
}